[
  {
    "author": "Pseudo Dionisio Areopagita",
    "chapter": 0,
    "greek": "ΤΩι ΣΥΜΠΡΕΣΒΥΤΕΡΩι ΤΙΜΟΘΕΩι ∆ΙΟΝΥΣΙΟΣ Ο ΠΡΕΣΒΥΤΕΡΟΣ",
    "lines": [
      1
    ],
    "section": 0,
    "spanish": "A Timoteo, el co-anciano, Dionisio el anciano.",
    "title": "De Caelesti Hierarchia",
    "notes": "ΣΥΜΠΡΕΣΒΥΤΕΡΩι (sympresbyterōi) significa 'co-anciano' o 'compañero en el presbiterado'.  Este saludo indica una relación de compañerismo y respeto mutuo entre Dionisio y Timoteo."
  },
  {
    "author": "Pseudo Dionisio Areopagita",
    "chapter": 0,
    "greek": "ΠΕΡΙ ΤΗΣ ΟΥΡΑΝΙΑΣ ΙΕΡΑΡΧΙΑΣ",
    "lines": [
      2
    ],
    "section": 0,
    "spanish": "Sobre la Jerarquía Celestial.",
    "title": "De Caelesti Hierarchia",
    "notes": "ΟΥΡΑΝΙΑΣ (ouranias) significa 'celestial' o 'del cielo'. ΙΕΡΑΡΧΙΑΣ (ierarchias) se traduce como 'jerarquía', un sistema ordenado de rangos o niveles. El título anticipa el tema central del tratado: la estructura jerárquica del reino celestial."
  }
]